rppy/__init__.py
rppy/db/__init__.py
rppy/db/append_only.py
rppy/db/base_class.py
rppy/db/crud.py
rppy/db/dal.py
rppy/db/regular_crud.py
rppy/db/session.py
rppy-0.0.2.dist-info/LICENSE
rppy-0.0.2.dist-info/METADATA
rppy-0.0.2.dist-info/WHEEL
rppy-0.0.2.dist-info/top_level.txt
rppy-0.0.2.dist-info/RECORD
