Metadata-Version: 2.1
Name: rppy
Version: 0.0.2
Summary: Remedy Product python library
Home-page: https://github.com/remedyproduct/rppy
Author: Remedy Product Team
Author-email: info@remedyproduct.com
License: UNKNOWN
Platform: UNKNOWN
Classifier: Programming Language :: Python :: 3
Classifier: Operating System :: OS Independent
Classifier: License :: OSI Approved :: MIT License
Requires-Python: >=3.7
Requires-Dist: sqlalchemy (>=1.3.5)
